LICENSE
poetry2conda/__init__.py
poetry2conda/convert.py
poetry2conda-0.3.0.dist-info/entry_points.txt
poetry2conda-0.3.0.dist-info/LICENSE
poetry2conda-0.3.0.dist-info/WHEEL
poetry2conda-0.3.0.dist-info/METADATA
poetry2conda-0.3.0.dist-info/RECORD
