Metadata-Version: 2.1
Name: poetry2conda
Version: 0.3.0
Summary: Convert pyproject.toml to environment.yaml
Home-page: https://github.com/dojeda/poetry2conda
License: MIT
Keywords: poetry,anaconda
Author: David Ojeda
Author-email: david.ojeda@gmail.com
Requires-Python: >=3.6,<4.0
Classifier: Development Status :: 3 - Alpha
Classifier: Environment :: Console
Classifier: Intended Audience :: Developers
Classifier: License :: OSI Approved :: MIT License
Classifier: Operating System :: OS Independent
Classifier: Programming Language :: Python :: 3
Classifier: Programming Language :: Python :: 3 :: Only
Classifier: Programming Language :: Python :: 3.6
Classifier: Programming Language :: Python :: 3.7
Classifier: Programming Language :: Python :: 3.8
Requires-Dist: poetry-semver (>=0.1.0,<0.2.0)
Requires-Dist: toml (>=0.10.0,<0.11.0)
Project-URL: Repository, https://github.com/dojeda/poetry2conda
